LICENSE
cz_legacy/__init__.py
cz_legacy/_runtime_type_check_setup.py
cz_legacy/cz_legacy.py
cz_legacy/py.typed
cz_legacy-2.0.2.dist-info/LICENSE
cz_legacy-2.0.2.dist-info/METADATA
cz_legacy-2.0.2.dist-info/WHEEL
cz_legacy-2.0.2.dist-info/entry_points.txt
cz_legacy-2.0.2.dist-info/RECORD
