Metadata-Version: 2.1
Name: cz_legacy
Version: 2.0.2
Summary: Extends Conventional Commits Change Types with User-Defined Legacy Types for Commitizen
Home-page: https://github.com/kyleking/cz_legacy
License: MIT
Keywords: calcipy_template,commitizen,conventional commits,git
Author: Kyle King
Author-email: dev.act.kyle@gmail.com
Requires-Python: >=3.8,<4.0
Classifier: Development Status :: 5 - Production/Stable
Classifier: Intended Audience :: Developers
Classifier: License :: OSI Approved :: MIT License
Classifier: Operating System :: OS Independent
Classifier: Programming Language :: Python :: 3
Classifier: Programming Language :: Python :: 3.8
Classifier: Programming Language :: Python :: 3.9
Classifier: Programming Language :: Python :: 3.10
Classifier: Programming Language :: Python :: 3.11
Classifier: Programming Language :: Python :: 3.12
Classifier: Programming Language :: Python :: Implementation :: CPython
Requires-Dist: commitizen (>=3.27.0)
Requires-Dist: typing-extensions (>=4.12.2)
Project-URL: Bug Tracker, https://github.com/kyleking/cz_legacy/issues
Project-URL: Changelog, https://github.com/kyleking/cz_legacy/blob/main/docs/docs/CHANGELOG.md
Project-URL: Documentation, https://cz_legacy.kyleking.me
Project-URL: Repository, https://github.com/kyleking/cz_legacy
